[
    [{
        "title": "分类：",
        "ul": [
            "全部",
            "11.11爆品清单",
            "今日特价",
            "秋冬热卖",
            "上衣",
            "下装",
            "裙装",
            "爬服连体衣",
            "内衣/配搭",
            "儿童鞋",
            "学步鞋",
            "洗护",
            "喂养",
            "孕产内衣",
            "妈咪用品",
            "孕妈装",
            "玩具",
            "图书",
            "推车/童车",
            "安全座椅",
            "童包",
            "儿童雨具/泳具",
            "婴童床品套件",
            "婴童被枕芯类",
            "抱被睡袋",
            "儿童家具收纳"
        ]
    }, {
        "title": "配送地区：",
        "ul": [
            "全部",
            "香港",
            "澳门",
            "台湾",
            "日韩",
            "欧洲"
        ]
    }, {
        "title": "排序：",
        "ul": [
            "默认",
            "价格",
            "上架时间"
        ]
    }],
    [{
            "bt": {
                "title": "11.11爆品清单",
                "subtitle": "婴童爆品盘点"
            },
            "nr": [{
                "imga": "https://yanxuan-item.nosdn.127.net/5bce7b177e77e56d3bec054981500d9a.png?imageView&quality=95&thumbnail=245x245",
                "imgb": "https://yanxuan-item.nosdn.127.net/1a58a34fce528994902d890f53a8efdd.jpg?quality=95&thumbnail=245x245&imageView",
                "promoLogo": "https://yanxuan.nosdn.127.net/bf43c8b8b8c205b14e3ac27021e04394.png",
                "promBanner": "https://yanxuan.nosdn.127.net/5e5ba7f9c3805cc8085368ed41aaff65.png",
                "promTitle": "https://yanxuan.nosdn.127.net/ced6f7cfbd566e260ea67ec486cb9b60.png",
                "name": "11.11",
                "price": "定金预售",
                "promContent": "99抵409 仅剩2天",
                "itemTag": "定金购",
                "name2": "浓缩即食燕窝4盒囤货装",
                "price2": "¥999",
                "counterPrice": "¥1309",
                "desc": "浓缩精炖，进口燕条"
            }, {
                "imga": "https://yanxuan-item.nosdn.127.net/5536fb0a507b16d8eb37f82cb7fb6f69.png?imageView&quality=95&thumbnail=245x245",
                "imgb": "https://yanxuan-item.nosdn.127.net/3449b46c4726e65cd92a67a0828325a3.jpg?quality=95&thumbnail=245x245&imageView",
                "promoLogo": "https://yanxuan.nosdn.127.net/bf43c8b8b8c205b14e3ac27021e04394.png",
                "promBanner": "https://yanxuan.nosdn.127.net/5e5ba7f9c3805cc8085368ed41aaff65.png",
                "promTitle": "https://yanxuan.nosdn.127.net/ced6f7cfbd566e260ea67ec486cb9b60.png",
                "name": "11.11",
                "price": "定金预售",
                "promContent": "99抵409 仅剩2天",
                "itemTag": "定金购",
                "name2": "浓缩即食燕窝4盒囤货装",
                "price2": "¥999",
                "counterPrice": "¥1309",
                "desc": "浓缩精炖，进口燕条"
            }, {
                "imga": "https://yanxuan-item.nosdn.127.net/98d91acbfdd456c536e8f44f87d349c1.png?imageView&quality=95&thumbnail=245x245",
                "imgb": "https://yanxuan-item.nosdn.127.net/3ce12780d4b0c65771db9be89d7bbc3e.jpg?quality=95&thumbnail=245x245&imageView",
                "promoLogo": "https://yanxuan.nosdn.127.net/bf43c8b8b8c205b14e3ac27021e04394.png",
                "promBanner": "https://yanxuan.nosdn.127.net/d03b0828cbcc0a64b4c89c8c9c5e6345.png",
                "promTitle": "https://yanxuan.nosdn.127.net/879ed370f7374379256c00673dab7835.png",
                "name": "11.11",
                "price": "定金预售",
                "promContent": "99抵409 仅剩2天",
                "itemTag": "定金购",
                "name2": "浓缩即食燕窝4盒囤货装",
                "price2": "¥999",
                "counterPrice": "¥1309",
                "desc": "浓缩精炖，进口燕条"
            }, {
                "imga": "https://yanxuan-item.nosdn.127.net/c7f4cb779e3c6ebb6eb9afbfff955b51.png?imageView&quality=95&thumbnail=245x245",
                "imgb": "https://yanxuan-item.nosdn.127.net/d2a2d0bfdbb5e9db3d062129a9462500.jpg?quality=95&thumbnail=245x245&imageView",
                "promoLogo": "https://yanxuan.nosdn.127.net/bf43c8b8b8c205b14e3ac27021e04394.png",
                "promBanner": "https://yanxuan.nosdn.127.net/d03b0828cbcc0a64b4c89c8c9c5e6345.png",
                "promTitle": "https://yanxuan.nosdn.127.net/879ed370f7374379256c00673dab7835.png",
                "name": "11.11",
                "price": "定金预售",
                "promContent": "99抵409 仅剩2天",
                "itemTag": "定金购",
                "name2": "浓缩即食燕窝4盒囤货装",
                "price2": "¥999",
                "counterPrice": "¥1309",
                "desc": "浓缩精炖，进口燕条"
            }, {
                "imga": "https://yanxuan-item.nosdn.127.net/5b25091fca788b5119495c9aadc46f77.png?imageView&quality=95&thumbnail=245x245",
                "imgb": "https://yanxuan-item.nosdn.127.net/4114d5ecb60d42c7b802bc9b355fbbc5.jpg?quality=95&thumbnail=245x245&imageView",
                "promoLogo": "https://yanxuan.nosdn.127.net/bf43c8b8b8c205b14e3ac27021e04394.png",
                "promBanner": "https://yanxuan.nosdn.127.net/5e5ba7f9c3805cc8085368ed41aaff65.png",
                "promTitle": "https://yanxuan.nosdn.127.net/ced6f7cfbd566e260ea67ec486cb9b60.png",
                "name": "11.11",
                "price": "定金预售",
                "promContent": "99抵409 仅剩2天",
                "itemTag": "定金购",
                "name2": "浓缩即食燕窝4盒囤货装",
                "price2": "¥999",
                "counterPrice": "¥1309",
                "desc": "浓缩精炖，进口燕条"
            }, {
                "imga": "https://yanxuan-item.nosdn.127.net/5ad9bbe5ef47a9c28607b350ec82d289.png?imageView&quality=95&thumbnail=245x245",
                "imgb": "https://yanxuan-item.nosdn.127.net/1cd20a5e65726003819e6e484c4c8b17.jpg?quality=95&thumbnail=245x245&imageView",
                "promoLogo": "https://yanxuan.nosdn.127.net/bf43c8b8b8c205b14e3ac27021e04394.png",
                "promBanner": "https://yanxuan.nosdn.127.net/5e5ba7f9c3805cc8085368ed41aaff65.png",
                "promTitle": "https://yanxuan.nosdn.127.net/ced6f7cfbd566e260ea67ec486cb9b60.png",
                "name": "11.11",
                "price": "定金预售",
                "promContent": "99抵409 仅剩2天",
                "itemTag": "定金购",
                "name2": "浓缩即食燕窝4盒囤货装",
                "price2": "¥999",
                "counterPrice": "¥1309",
                "desc": "浓缩精炖，进口燕条"
            }, {
                "imga": "https://yanxuan-item.nosdn.127.net/8400991528a5a6eb71a81b8c1e2d5346.png?imageView&quality=95&thumbnail=245x245",
                "imgb": "https://yanxuan-item.nosdn.127.net/4f1096d9d358eadf99f01b832e3652b7.jpg?quality=95&thumbnail=245x245&imageView",
                "promoLogo": "https://yanxuan.nosdn.127.net/bf43c8b8b8c205b14e3ac27021e04394.png",
                "promBanner": "https://yanxuan.nosdn.127.net/5e5ba7f9c3805cc8085368ed41aaff65.png",
                "promTitle": "https://yanxuan.nosdn.127.net/ced6f7cfbd566e260ea67ec486cb9b60.png",
                "name": "11.11",
                "price": "定金预售",
                "promContent": "99抵409 仅剩2天",
                "itemTag": "定金购",
                "name2": "浓缩即食燕窝4盒囤货装",
                "price2": "¥999",
                "counterPrice": "¥1309",
                "desc": "浓缩精炖，进口燕条"
            }, {
                "imga": "https://yanxuan-item.nosdn.127.net/956d967509bd8cb8b477a92db62480b9.png?imageView&quality=95&thumbnail=245x245",
                "imgb": "https://yanxuan-item.nosdn.127.net/0bb0dfb0e0e853d18047034032166c30.jpg?quality=95&thumbnail=245x245&imageView",
                "promoLogo": "https://yanxuan.nosdn.127.net/bf43c8b8b8c205b14e3ac27021e04394.png",
                "promBanner": "https://yanxuan.nosdn.127.net/5e5ba7f9c3805cc8085368ed41aaff65.png",
                "promTitle": "https://yanxuan.nosdn.127.net/ced6f7cfbd566e260ea67ec486cb9b60.png",
                "name": "11.11",
                "price": "定金预售",
                "promContent": "99抵409 仅剩2天",
                "itemTag": "定金购",
                "name2": "浓缩即食燕窝4盒囤货装",
                "price2": "¥999",
                "counterPrice": "¥1309",
                "desc": "浓缩精炖，进口燕条"
            }, {
                "imga": "https://yanxuan-item.nosdn.127.net/a1bb09b4fb29b882f5ad9a1dd1d9bb07.png?imageView&quality=95&thumbnail=245x245",
                "imgb": "https://yanxuan-item.nosdn.127.net/b376fabd965eb07103abf209d466d48c.jpg?quality=95&thumbnail=245x245&imageView",
                "promoLogo": "https://yanxuan.nosdn.127.net/bf43c8b8b8c205b14e3ac27021e04394.png",
                "promBanner": "https://yanxuan.nosdn.127.net/5e5ba7f9c3805cc8085368ed41aaff65.png",
                "promTitle": "https://yanxuan.nosdn.127.net/ced6f7cfbd566e260ea67ec486cb9b60.png",
                "name": "11.11",
                "price": "定金预售",
                "promContent": "99抵409 仅剩2天",
                "itemTag": "定金购",
                "name2": "浓缩即食燕窝4盒囤货装",
                "price2": "¥999",
                "counterPrice": "¥1309",
                "desc": "浓缩精炖，进口燕条"
            }, {
                "imga": "https://yanxuan-item.nosdn.127.net/daf77da84fe1068116359f0f198b8127.png?imageView&quality=95&thumbnail=245x245",
                "imgb": "https://yanxuan-item.nosdn.127.net/dfb8358b83e8014d1053fe4437cd51c6.jpg?quality=95&thumbnail=245x245&imageView",
                "promoLogo": "https://yanxuan.nosdn.127.net/bf43c8b8b8c205b14e3ac27021e04394.png",
                "promBanner": "https://yanxuan.nosdn.127.net/5e5ba7f9c3805cc8085368ed41aaff65.png",
                "promTitle": "https://yanxuan.nosdn.127.net/ced6f7cfbd566e260ea67ec486cb9b60.png",
                "name": "11.11",
                "price": "定金预售",
                "promContent": "99抵409 仅剩2天",
                "itemTag": "定金购",
                "name2": "浓缩即食燕窝4盒囤货装",
                "price2": "¥999",
                "counterPrice": "¥1309",
                "desc": "浓缩精炖，进口燕条"
            }, {
                "imga": "https://yanxuan-item.nosdn.127.net/f32e746fe285bbbbb989c7f1aaef774d.png?imageView&quality=95&thumbnail=245x245",
                "imgb": "https://yanxuan-item.nosdn.127.net/69df1c2e8c38452f391b089a6a552072.jpg?quality=95&thumbnail=245x245&imageView",
                "promoLogo": "https://yanxuan.nosdn.127.net/bf43c8b8b8c205b14e3ac27021e04394.png",
                "promBanner": "https://yanxuan.nosdn.127.net/5e5ba7f9c3805cc8085368ed41aaff65.png",
                "promTitle": "https://yanxuan.nosdn.127.net/ced6f7cfbd566e260ea67ec486cb9b60.png",
                "name": "11.11",
                "price": "定金预售",
                "promContent": "99抵409 仅剩2天",
                "itemTag": "定金购",
                "name2": "浓缩即食燕窝4盒囤货装",
                "price2": "¥999",
                "counterPrice": "¥1309",
                "desc": "浓缩精炖，进口燕条"
            }, {
                "imga": "https://yanxuan-item.nosdn.127.net/0b3d842ef539efd4d5418fc1ecd157aa.png?imageView&quality=95&thumbnail=245x245",
                "imgb": "https://yanxuan-item.nosdn.127.net/bbe9ad5da097ebc42e6ebc2a262387af.jpg?quality=95&thumbnail=245x245&imageView",
                "promoLogo": "https://yanxuan.nosdn.127.net/bf43c8b8b8c205b14e3ac27021e04394.png",
                "promBanner": "https://yanxuan.nosdn.127.net/5e5ba7f9c3805cc8085368ed41aaff65.png",
                "promTitle": "https://yanxuan.nosdn.127.net/ced6f7cfbd566e260ea67ec486cb9b60.png",
                "name": "11.11",
                "price": "定金预售",
                "promContent": "99抵409 仅剩2天",
                "itemTag": "定金购",
                "name2": "浓缩即食燕窝4盒囤货装",
                "price2": "¥999",
                "counterPrice": "¥1309",
                "desc": "浓缩精炖，进口燕条"
            }, {
                "imga": "https://yanxuan-item.nosdn.127.net/4adb5631f41962e7a5e5e1a201e6ecf3.png?imageView&quality=95&thumbnail=245x245",
                "imgb": "https://yanxuan-item.nosdn.127.net/39f3eee54df57b0398bcf8de07a73b22.jpg?quality=95&thumbnail=245x245&imageView",
                "promoLogo": "https://yanxuan.nosdn.127.net/bf43c8b8b8c205b14e3ac27021e04394.png",
                "promBanner": "https://yanxuan.nosdn.127.net/5e5ba7f9c3805cc8085368ed41aaff65.png",
                "promTitle": "https://yanxuan.nosdn.127.net/ced6f7cfbd566e260ea67ec486cb9b60.png",
                "name": "11.11",
                "price": "定金预售",
                "promContent": "99抵409 仅剩2天",
                "itemTag": "定金购",
                "name2": "浓缩即食燕窝4盒囤货装",
                "price2": "¥999",
                "counterPrice": "¥1309",
                "desc": "浓缩精炖，进口燕条"
            }, {
                "imga": "https://yanxuan-item.nosdn.127.net/4b4d2b89cad3417135b46976b7de0123.png?imageView&quality=95&thumbnail=245x245",
                "imgb": "https://yanxuan-item.nosdn.127.net/805e112581a1a579c6e5d649e18720df.jpg?quality=95&thumbnail=245x245&imageView",
                "promoLogo": "https://yanxuan.nosdn.127.net/bf43c8b8b8c205b14e3ac27021e04394.png",
                "promBanner": "https://yanxuan.nosdn.127.net/5e5ba7f9c3805cc8085368ed41aaff65.png",
                "promTitle": "https://yanxuan.nosdn.127.net/ced6f7cfbd566e260ea67ec486cb9b60.png",
                "name": "11.11",
                "price": "定金预售",
                "promContent": "99抵409 仅剩2天",
                "itemTag": "定金购",
                "name2": "浓缩即食燕窝4盒囤货装",
                "price2": "¥999",
                "counterPrice": "¥1309",
                "desc": "浓缩精炖，进口燕条"
            }, {
                "imga": "https://yanxuan-item.nosdn.127.net/faeb1ffac79c50e78a93d9f47a6e1be9.png?imageView&quality=95&thumbnail=245x245",
                "imgb": "https://yanxuan-item.nosdn.127.net/20645c2fbd1e32624dad51c588121369.jpg?quality=95&thumbnail=245x245&imageView",
                "promoLogo": "https://yanxuan.nosdn.127.net/bf43c8b8b8c205b14e3ac27021e04394.png",
                "promBanner": "https://yanxuan.nosdn.127.net/d03b0828cbcc0a64b4c89c8c9c5e6345.png",
                "promTitle": "https://yanxuan.nosdn.127.net/879ed370f7374379256c00673dab7835.png",
                "name": "11.11",
                "price": "定金预售",
                "promContent": "99抵409 仅剩2天",
                "itemTag": "定金购",
                "name2": "浓缩即食燕窝4盒囤货装",
                "price2": "¥999",
                "counterPrice": "¥1309",
                "desc": "浓缩精炖，进口燕条"
            }, {
                "imga": "https://yanxuan-item.nosdn.127.net/429c8e4c92ecda0ec1ff1b9a9c03f687.png?imageView&quality=95&thumbnail=245x245",
                "imgb": "https://yanxuan-item.nosdn.127.net/394174852aeba982f071d80c1fb0eefb.jpg?quality=95&thumbnail=245x245&imageView",
                "promoLogo": "https://yanxuan.nosdn.127.net/bf43c8b8b8c205b14e3ac27021e04394.png",
                "promBanner": "https://yanxuan.nosdn.127.net/5e5ba7f9c3805cc8085368ed41aaff65.png",
                "promTitle": "https://yanxuan.nosdn.127.net/ced6f7cfbd566e260ea67ec486cb9b60.png",
                "name": "11.11",
                "price": "定金预售",
                "promContent": "99抵409 仅剩2天",
                "itemTag": "定金购",
                "name2": "浓缩即食燕窝4盒囤货装",
                "price2": "¥999",
                "counterPrice": "¥1309",
                "desc": "浓缩精炖，进口燕条"
            }, {
                "imga": "https://yanxuan-item.nosdn.127.net/bd9656bf8dab5a9de8c6864edf39aac4.png?imageView&quality=95&thumbnail=245x245",
                "imgb": "https://yanxuan-item.nosdn.127.net/00bde4d78f94639dc9cc8aeaeffedcbc.jpg?quality=95&thumbnail=245x245&imageView",
                "promoLogo": "https://yanxuan.nosdn.127.net/bf43c8b8b8c205b14e3ac27021e04394.png",
                "promBanner": "https://yanxuan.nosdn.127.net/d03b0828cbcc0a64b4c89c8c9c5e6345.png",
                "promTitle": "https://yanxuan.nosdn.127.net/879ed370f7374379256c00673dab7835.png",
                "name": "11.11",
                "price": "定金预售",
                "promContent": "99抵409 仅剩2天",
                "itemTag": "定金购",
                "name2": "浓缩即食燕窝4盒囤货装",
                "price2": "¥999",
                "counterPrice": "¥1309",
                "desc": "浓缩精炖，进口燕条",
                "none": 222
            }, {
                "imga": "https://yanxuan-item.nosdn.127.net/8e0229d0791c1e5ffa2273ecde9eb67f.png?imageView&quality=95&thumbnail=245x245",
                "imgb": "https://yanxuan-item.nosdn.127.net/afc954d7eacec0678fa5f47feddace01.jpg?quality=95&thumbnail=245x245&imageView",
                "promoLogo": "https://yanxuan.nosdn.127.net/bf43c8b8b8c205b14e3ac27021e04394.png",
                "promBanner": "https://yanxuan.nosdn.127.net/5e5ba7f9c3805cc8085368ed41aaff65.png",
                "promTitle": "https://yanxuan.nosdn.127.net/ced6f7cfbd566e260ea67ec486cb9b60.png",
                "name": "11.11",
                "price": "定金预售",
                "promContent": "99抵409 仅剩2天",
                "itemTag": "定金购",
                "name2": "浓缩即食燕窝4盒囤货装",
                "price2": "¥999",
                "counterPrice": "¥1309",
                "desc": "浓缩精炖，进口燕条"
            }, {
                "imga": "https://yanxuan-item.nosdn.127.net/aeea23eca486be8b4f4118d71636507f.png?imageView&quality=95&thumbnail=245x245",
                "imgb": "https://yanxuan-item.nosdn.127.net/7da0ee7e9ef1e2d78cb2cbee93111eb2.jpg?quality=95&thumbnail=245x245&imageView",
                "promoLogo": "https://yanxuan.nosdn.127.net/bf43c8b8b8c205b14e3ac27021e04394.png",
                "promBanner": "https://yanxuan.nosdn.127.net/5e5ba7f9c3805cc8085368ed41aaff65.png",
                "promTitle": "https://yanxuan.nosdn.127.net/ced6f7cfbd566e260ea67ec486cb9b60.png",
                "name": "11.11",
                "price": "定金预售",
                "promContent": "99抵409 仅剩2天",
                "itemTag": "定金购",
                "name2": "浓缩即食燕窝4盒囤货装",
                "price2": "¥999",
                "counterPrice": "¥1309",
                "desc": "浓缩精炖，进口燕条",
                "none2": 333
            }, {
                "imga": "https://yanxuan-item.nosdn.127.net/e6681b4863072388c60912cd244655e2.png?imageView&quality=95&thumbnail=245x245",
                "imgb": "https://yanxuan-item.nosdn.127.net/09a6a96e633a7dd9844bb3647c568278.jpg?quality=95&thumbnail=245x245&imageView",
                "promoLogo": "https://yanxuan.nosdn.127.net/bf43c8b8b8c205b14e3ac27021e04394.png",
                "promBanner": "https://yanxuan.nosdn.127.net/5e5ba7f9c3805cc8085368ed41aaff65.png",
                "promTitle": "https://yanxuan.nosdn.127.net/ced6f7cfbd566e260ea67ec486cb9b60.png",
                "name": "11.11",
                "price": "定金预售",
                "promContent": "99抵409 仅剩2天",
                "itemTag": "定金购",
                "name2": "浓缩即食燕窝4盒囤货装",
                "price2": "¥999",
                "counterPrice": "¥1309",
                "desc": "浓缩精炖，进口燕条"
            }, {
                "imga": "https://yanxuan-item.nosdn.127.net/12fedfeef872106dbe302c92ff013be0.png?imageView&quality=95&thumbnail=245x245",
                "imgb": "https://yanxuan-item.nosdn.127.net/06c9b2cdd87daba8f79c0baa43a7f8d3.jpg?quality=95&thumbnail=245x245&imageView",
                "promoLogo": "https://yanxuan.nosdn.127.net/bf43c8b8b8c205b14e3ac27021e04394.png",
                "promBanner": "https://yanxuan.nosdn.127.net/d03b0828cbcc0a64b4c89c8c9c5e6345.png",
                "promTitle": "https://yanxuan.nosdn.127.net/879ed370f7374379256c00673dab7835.png",
                "name": "11.11",
                "price": "定金预售",
                "promContent": "99抵409 仅剩2天",
                "itemTag": "定金购",
                "name2": "浓缩即食燕窝4盒囤货装",
                "price2": "¥999",
                "counterPrice": "¥1309",
                "desc": "浓缩精炖，进口燕条",
                "none1": 111
            }, {
                "imga": "https://yanxuan-item.nosdn.127.net/6f5869bee08c1337d41ea4c979b32028.png?imageView&quality=95&thumbnail=245x245",
                "imgb": "https://yanxuan-item.nosdn.127.net/eae07212f274d5d3f82bf20956001648.png?quality=95&thumbnail=245x245&imageView",
                "promoLogo": "https://yanxuan.nosdn.127.net/bf43c8b8b8c205b14e3ac27021e04394.png",
                "promBanner": "https://yanxuan.nosdn.127.net/d03b0828cbcc0a64b4c89c8c9c5e6345.png",
                "promTitle": "https://yanxuan.nosdn.127.net/879ed370f7374379256c00673dab7835.png",
                "name": "11.11",
                "price": "定金预售",
                "promContent": "99抵409 仅剩2天",
                "itemTag": "定金购",
                "name2": "浓缩即食燕窝4盒囤货装",
                "price2": "¥999",
                "counterPrice": "¥1309",
                "desc": "浓缩精炖，进口燕条",
                "none": 222
            }, {
                "imga": "https://yanxuan-item.nosdn.127.net/e79951803e92124b516d57a38397f962.png?imageView&quality=95&thumbnail=245x245",
                "imgb": "https://yanxuan-item.nosdn.127.net/59be7d6de92bdeecf0cee4b7265ac916.jpg?quality=95&thumbnail=245x245&imageView",
                "promoLogo": "https://yanxuan.nosdn.127.net/bf43c8b8b8c205b14e3ac27021e04394.png",
                "promBanner": "https://yanxuan.nosdn.127.net/5e5ba7f9c3805cc8085368ed41aaff65.png",
                "promTitle": "https://yanxuan.nosdn.127.net/ced6f7cfbd566e260ea67ec486cb9b60.png",
                "name": "11.11",
                "price": "定金预售",
                "promContent": "99抵409 仅剩2天",
                "itemTag": "定金购",
                "name2": "浓缩即食燕窝4盒囤货装",
                "price2": "¥999",
                "counterPrice": "¥1309",
                "desc": "浓缩精炖，进口燕条"
            }, {
                "imga": "https://yanxuan-item.nosdn.127.net/2496bd5088d3c8533e5b6a89c63b2193.png?imageView&quality=95&thumbnail=245x245",
                "imgb": "https://yanxuan-item.nosdn.127.net/e442262a9232341b856ac8acb2907a47.png?quality=95&thumbnail=245x245&imageView",
                "promoLogo": "https://yanxuan.nosdn.127.net/bf43c8b8b8c205b14e3ac27021e04394.png",
                "promBanner": "https://yanxuan.nosdn.127.net/5e5ba7f9c3805cc8085368ed41aaff65.png",
                "promTitle": "https://yanxuan.nosdn.127.net/ced6f7cfbd566e260ea67ec486cb9b60.png",
                "name": "11.11",
                "price": "定金预售",
                "promContent": "99抵409 仅剩2天",
                "itemTag": "定金购",
                "name2": "浓缩即食燕窝4盒囤货装",
                "price2": "¥999",
                "counterPrice": "¥1309",
                "desc": "浓缩精炖，进口燕条"
            }, {
                "imga": "https://yanxuan-item.nosdn.127.net/19e252f40bf0975695ef638325b2a75a.png?imageView&quality=95&thumbnail=245x245",
                "imgb": "https://yanxuan-item.nosdn.127.net/72a73065257be6c0bb483ae0eb5e9b40.jpg?quality=95&thumbnail=245x245&imageView",
                "promoLogo": "https://yanxuan.nosdn.127.net/bf43c8b8b8c205b14e3ac27021e04394.png",
                "promBanner": "https://yanxuan.nosdn.127.net/5e5ba7f9c3805cc8085368ed41aaff65.png",
                "promTitle": "https://yanxuan.nosdn.127.net/ced6f7cfbd566e260ea67ec486cb9b60.png",
                "name": "11.11",
                "price": "定金预售",
                "promContent": "99抵409 仅剩2天",
                "itemTag": "定金购",
                "name2": "浓缩即食燕窝4盒囤货装",
                "price2": "¥999",
                "counterPrice": "¥1309",
                "desc": "浓缩精炖，进口燕条"
            }, {
                "imga": "https://yanxuan-item.nosdn.127.net/5e27836d8156e62064dfa3d442eb4d2a.png?imageView&quality=95&thumbnail=245x245",
                "imgb": "https://yanxuan-item.nosdn.127.net/2d102976777b02d687de895761b2d0de.jpg?quality=95&thumbnail=245x245&imageView",
                "promoLogo": "https://yanxuan.nosdn.127.net/bf43c8b8b8c205b14e3ac27021e04394.png",
                "promBanner": "https://yanxuan.nosdn.127.net/5e5ba7f9c3805cc8085368ed41aaff65.png",
                "promTitle": "https://yanxuan.nosdn.127.net/ced6f7cfbd566e260ea67ec486cb9b60.png",
                "name": "11.11",
                "price": "定金预售",
                "promContent": "99抵409 仅剩2天",
                "itemTag": "定金购",
                "name2": "浓缩即食燕窝4盒囤货装",
                "price2": "¥999",
                "counterPrice": "¥1309",
                "desc": "浓缩精炖，进口燕条"
            }, {
                "imga": "https://yanxuan-item.nosdn.127.net/cb8afb98658ad322482c703b6fe8c183.png?imageView&quality=95&thumbnail=245x245",
                "imgb": "https://yanxuan-item.nosdn.127.net/9b8b4cd3037cff58a7248910dbc36e7b.jpg?quality=95&thumbnail=245x245&imageView",
                "promoLogo": "https://yanxuan.nosdn.127.net/bf43c8b8b8c205b14e3ac27021e04394.png",
                "promBanner": "https://yanxuan.nosdn.127.net/d03b0828cbcc0a64b4c89c8c9c5e6345.png",
                "promTitle": "https://yanxuan.nosdn.127.net/879ed370f7374379256c00673dab7835.png",
                "name": "11.11",
                "price": "定金预售",
                "promContent": "99抵409 仅剩2天",
                "itemTag": "定金购",
                "name2": "浓缩即食燕窝4盒囤货装",
                "price2": "¥999",
                "counterPrice": "¥1309",
                "desc": "浓缩精炖，进口燕条",
                "none1": 111
            }, {
                "imga": "https://yanxuan-item.nosdn.127.net/a1c540b60df55ba692c919bb7035b8a0.png?imageView&quality=95&thumbnail=245x245",
                "imgb": "https://yanxuan-item.nosdn.127.net/ea93bdc161183d1c67b2d0ba96b57479.jpg?quality=95&thumbnail=245x245&imageView",
                "promoLogo": "https://yanxuan.nosdn.127.net/bf43c8b8b8c205b14e3ac27021e04394.png",
                "promBanner": "https://yanxuan.nosdn.127.net/5e5ba7f9c3805cc8085368ed41aaff65.png",
                "promTitle": "https://yanxuan.nosdn.127.net/ced6f7cfbd566e260ea67ec486cb9b60.png",
                "name": "11.11",
                "price": "定金预售",
                "promContent": "99抵409 仅剩2天",
                "itemTag": "定金购",
                "name2": "浓缩即食燕窝4盒囤货装",
                "price2": "¥999",
                "counterPrice": "¥1309",
                "desc": "浓缩精炖，进口燕条"
            }, {
                "imga": "https://yanxuan-item.nosdn.127.net/365780a64e347e836de188a6b8470aa9.png?imageView&quality=95&thumbnail=245x245",
                "imgb": "https://yanxuan-item.nosdn.127.net/aee214c98020aae5a41a16dfaeaa671f.jpg?quality=95&thumbnail=245x245&imageView",
                "promoLogo": "https://yanxuan.nosdn.127.net/bf43c8b8b8c205b14e3ac27021e04394.png",
                "promBanner": "https://yanxuan.nosdn.127.net/5e5ba7f9c3805cc8085368ed41aaff65.png",
                "promTitle": "https://yanxuan.nosdn.127.net/ced6f7cfbd566e260ea67ec486cb9b60.png",
                "name": "11.11",
                "price": "定金预售",
                "promContent": "99抵409 仅剩2天",
                "itemTag": "定金购",
                "name2": "浓缩即食燕窝4盒囤货装",
                "price2": "¥999",
                "counterPrice": "¥1309",
                "desc": "浓缩精炖，进口燕条"
            }, {
                "imga": "https://yanxuan-item.nosdn.127.net/3e56dcb71fc8711195817884d2f413af.png?imageView&quality=95&thumbnail=245x245",
                "imgb": "https://yanxuan-item.nosdn.127.net/612a348a6cbbee5018d801b1d8bdc166.jpg?quality=95&thumbnail=245x245&imageView",
                "promoLogo": "https://yanxuan.nosdn.127.net/bf43c8b8b8c205b14e3ac27021e04394.png",
                "promBanner": "https://yanxuan.nosdn.127.net/5e5ba7f9c3805cc8085368ed41aaff65.png",
                "promTitle": "https://yanxuan.nosdn.127.net/ced6f7cfbd566e260ea67ec486cb9b60.png",
                "name": "11.11",
                "price": "定金预售",
                "promContent": "99抵409 仅剩2天",
                "itemTag": "定金购",
                "name2": "浓缩即食燕窝4盒囤货装",
                "price2": "¥999",
                "counterPrice": "¥1309",
                "desc": "浓缩精炖，进口燕条"
            }, {
                "imga": "https://yanxuan-item.nosdn.127.net/5f968041c16889ada9d6b0108de936aa.png?imageView&quality=95&thumbnail=245x245",
                "imgb": "https://yanxuan-item.nosdn.127.net/d022087faa31de36ac5c67ad947bf401.jpg?quality=95&thumbnail=245x245&imageView",
                "promoLogo": "https://yanxuan.nosdn.127.net/bf43c8b8b8c205b14e3ac27021e04394.png",
                "promBanner": "https://yanxuan.nosdn.127.net/5e5ba7f9c3805cc8085368ed41aaff65.png",
                "promTitle": "https://yanxuan.nosdn.127.net/ced6f7cfbd566e260ea67ec486cb9b60.png",
                "name": "11.11",
                "price": "定金预售",
                "promContent": "99抵409 仅剩2天",
                "itemTag": "定金购",
                "name2": "浓缩即食燕窝4盒囤货装",
                "price2": "¥999",
                "counterPrice": "¥1309",
                "desc": "浓缩精炖，进口燕条"
            }, {
                "imga": "https://yanxuan-item.nosdn.127.net/1870a141a24f16c0e6be7ecd2b59088b.png?imageView&quality=95&thumbnail=245x245",
                "imgb": "https://yanxuan-item.nosdn.127.net/6125cef1592e9fef5ce6098ee2663a0e.jpg?quality=95&thumbnail=245x245&imageView",
                "promoLogo": "https://yanxuan.nosdn.127.net/bf43c8b8b8c205b14e3ac27021e04394.png",
                "promBanner": "https://yanxuan.nosdn.127.net/5e5ba7f9c3805cc8085368ed41aaff65.png",
                "promTitle": "https://yanxuan.nosdn.127.net/ced6f7cfbd566e260ea67ec486cb9b60.png",
                "name": "11.11",
                "price": "定金预售",
                "promContent": "99抵409 仅剩2天",
                "itemTag": "定金购",
                "name2": "浓缩即食燕窝4盒囤货装",
                "price2": "¥999",
                "counterPrice": "¥1309",
                "desc": "浓缩精炖，进口燕条"
            }]
        },
        {
            "bt": {
                "title": "今日特价",
                "subtitle": "聪明爸妈这么买"
            },
            "nr": [{
                    "imga": "https://yanxuan-item.nosdn.127.net/1deb455e7a04331c59d32ced4d7cd206.png?imageView&quality=95&thumbnail=245x245",
                    "imgb": "https://yanxuan-item.nosdn.127.net/b126b7069efbe164ec72003f6f5c98ff.jpg?quality=95&thumbnail=245x245&imageView",
                    "promoLogo": "https://yanxuan.nosdn.127.net/bf43c8b8b8c205b14e3ac27021e04394.png",
                    "promBanner": "https://yanxuan.nosdn.127.net/5e5ba7f9c3805cc8085368ed41aaff65.png",
                    "promTitle": "https://yanxuan.nosdn.127.net/ced6f7cfbd566e260ea67ec486cb9b60.png",
                    "name": "狂欢特惠",
                    "price": "¥99",
                    "promContent": "仅剩7天",
                    "itemTag": "狂欢特惠",
                    "name2": "996五宝茶",
                    "price2": "¥99",
                    "counterPrice": "¥139",
                    "desc": "添加玛咖粉，找回理想状态"
                },
                {
                    "imga": "https://yanxuan-item.nosdn.127.net/30e5f961d57ba90e486a2f0ecd45fbc1.png?imageView&quality=95&thumbnail=245x245",
                    "imgb": "https://yanxuan-item.nosdn.127.net/a7e05a0fb3264403aa0cf86ef5b5c1d6.jpg?quality=95&thumbnail=245x245&imageView",
                    "promoLogo": "https://yanxuan.nosdn.127.net/bf43c8b8b8c205b14e3ac27021e04394.png",
                    "promBanner": "https://yanxuan.nosdn.127.net/5e5ba7f9c3805cc8085368ed41aaff65.png",
                    "promTitle": "https://yanxuan.nosdn.127.net/ced6f7cfbd566e260ea67ec486cb9b60.png",
                    "price": "¥99",
                    "promContent": "仅剩7天",
                    "itemTag": "狂欢特惠",
                    "name2": "996五宝茶",
                    "price2": "¥99",
                    "counterPrice": "¥139",
                    "desc": "添加玛咖粉，找回理想状态"
                },
                {
                    "imga": "https://yanxuan-item.nosdn.127.net/4dc4ae172d99bc3c6b87da7db6978060.png?imageView&quality=95&thumbnail=245x245",
                    "imgb": "https://yanxuan-item.nosdn.127.net/f3d4c7b947816b5405fddc20d46740b3.jpg?quality=95&thumbnail=245x245&imageView",
                    "promoLogo": "https://yanxuan.nosdn.127.net/bf43c8b8b8c205b14e3ac27021e04394.png",
                    "promBanner": "https://yanxuan.nosdn.127.net/5e5ba7f9c3805cc8085368ed41aaff65.png",
                    "promTitle": "https://yanxuan.nosdn.127.net/ced6f7cfbd566e260ea67ec486cb9b60.png",
                    "price": "¥29.8",
                    "promContent": "11月10日 22点开抢",
                    "itemTag": "好货内部价",
                    "name2": "蜜桃米露 750毫升",
                    "price2": "￥38",
                    "counterPrice": "¥499",
                    "desc": "蜜桃味江南米酒，初恋味道"
                },
                {

                    "imga": "https://yanxuan-item.nosdn.127.net/95ccd79e82c9a154f8a58a18a4ec09de.png?imageView&quality=95&thumbnail=245x245",
                    "imgb": "https://yanxuan-item.nosdn.127.net/b937b5ed3b3469a24ad8b524907366e3.jpg?quality=95&thumbnail=245x245&imageView",
                    "promoLogo": "https://yanxuan.nosdn.127.net/bf43c8b8b8c205b14e3ac27021e04394.png",
                    "promBanner": "https://yanxuan.nosdn.127.net/5e5ba7f9c3805cc8085368ed41aaff65.png",
                    "promTitle": "https://yanxuan.nosdn.127.net/ced6f7cfbd566e260ea67ec486cb9b60.png",
                    "name": "超级疯抢日",
                    "price": "¥29.8",
                    "promContent": "11月10日 22点开抢",
                    "itemTag": "好货内部价",
                    "name2": "蜜桃米露 750毫升",
                    "price2": "￥38",
                    "counterPrice": "¥499",
                    "desc": "蜜桃味江南米酒，初恋味道"
                },
                {
                    "imga": "https://yanxuan-item.nosdn.127.net/a1c540b60df55ba692c919bb7035b8a0.png?imageView&quality=95&thumbnail=245x245",
                    "imgb": "https://yanxuan-item.nosdn.127.net/ea93bdc161183d1c67b2d0ba96b57479.jpg?quality=95&thumbnail=245x245&imageView",
                    "promoLogo": "https://yanxuan.nosdn.127.net/bf43c8b8b8c205b14e3ac27021e04394.png",
                    "promBanner": "https://yanxuan.nosdn.127.net/5e5ba7f9c3805cc8085368ed41aaff65.png",
                    "promTitle": "https://yanxuan.nosdn.127.net/ced6f7cfbd566e260ea67ec486cb9b60.png",
                    "name": "超级疯抢日",
                    "price": "¥29.8",
                    "promContent": "11月10日 22点开抢",
                    "itemTag": "好货内部价",
                    "name2": "蜜桃米露 750毫升",
                    "price2": "￥38",
                    "counterPrice": "¥499",
                    "desc": "蜜桃味江南米酒，初恋味道"
                },
                {
                    "imga": "https://yanxuan-item.nosdn.127.net/429c8e4c92ecda0ec1ff1b9a9c03f687.png?imageView&quality=95&thumbnail=245x245",
                    "imgb": "https://yanxuan-item.nosdn.127.net/394174852aeba982f071d80c1fb0eefb.jpg?quality=95&thumbnail=245x245&imageView",
                    "promoLogo": "https://yanxuan.nosdn.127.net/bf43c8b8b8c205b14e3ac27021e04394.png",
                    "promBanner": "https://yanxuan.nosdn.127.net/5e5ba7f9c3805cc8085368ed41aaff65.png",
                    "promTitle": "https://yanxuan.nosdn.127.net/ced6f7cfbd566e260ea67ec486cb9b60.png",
                    "name": "好货内部价",
                    "price": "¥399",
                    "promContent": "仅剩3天",
                    "itemTag": "好货内部价",
                    "name2": "60s臻密绒磨毛四件套",
                    "price2": "¥499",
                    "counterPrice": "¥499",
                    "desc": "浅绒如脂臻密，高级莫兰迪色系"
                },
                {
                    "imga": "https://yanxuan-item.nosdn.127.net/e79951803e92124b516d57a38397f962.png?imageView&quality=95&thumbnail=245x245",
                    "imgb": "https://yanxuan-item.nosdn.127.net/59be7d6de92bdeecf0cee4b7265ac916.jpg?quality=95&thumbnail=245x245&imageView",
                    "promoLogo": "https://yanxuan.nosdn.127.net/bf43c8b8b8c205b14e3ac27021e04394.png",
                    "promBanner": "https://yanxuan.nosdn.127.net/5e5ba7f9c3805cc8085368ed41aaff65.png",
                    "promTitle": "https://yanxuan.nosdn.127.net/ced6f7cfbd566e260ea67ec486cb9b60.png",
                    "name": "狂欢特惠",
                    "price": "¥99",
                    "promContent": "仅剩7天",
                    "itemTag": "狂欢特惠",
                    "name2": "996五宝茶",
                    "price2": "¥99",
                    "counterPrice": "¥139",
                    "desc": "添加玛咖粉，找回理想状态"
                },
                {
                    "imga": "https://yanxuan-item.nosdn.127.net/53c44d269a22f9e3f6cf50d8757ce92e.png?imageView&quality=95&thumbnail=245x245",
                    "imgb": "https://yanxuan-item.nosdn.127.net/7775899950827cc507fe16980da473f5.jpg?quality=95&thumbnail=245x245&imageView",
                    "promoLogo": "https://yanxuan.nosdn.127.net/bf43c8b8b8c205b14e3ac27021e04394.png",
                    "promBanner": "https://yanxuan.nosdn.127.net/5e5ba7f9c3805cc8085368ed41aaff65.png",
                    "promTitle": "https://yanxuan.nosdn.127.net/ced6f7cfbd566e260ea67ec486cb9b60.png",
                    "name": "超级疯抢日",
                    "price": "¥29.8",
                    "promContent": "11月10日 22点开抢",
                    "itemTag": "好货内部价",
                    "name2": "蜜桃米露 750毫升",
                    "price2": "￥38",
                    "counterPrice": "¥499",
                    "desc": "蜜桃味江南米酒，初恋味道"
                },
                {
                    "imga": "https://yanxuan-item.nosdn.127.net/19e252f40bf0975695ef638325b2a75a.png?imageView&quality=95&thumbnail=245x245",
                    "imgb": "https://yanxuan-item.nosdn.127.net/72a73065257be6c0bb483ae0eb5e9b40.jpg?quality=95&thumbnail=245x245&imageView",
                    "promoLogo": "https://yanxuan.nosdn.127.net/bf43c8b8b8c205b14e3ac27021e04394.png",
                    "promBanner": "https://yanxuan.nosdn.127.net/5e5ba7f9c3805cc8085368ed41aaff65.png",
                    "promTitle": "https://yanxuan.nosdn.127.net/ced6f7cfbd566e260ea67ec486cb9b60.png",
                    "name": "超级疯抢日",
                    "price": "¥29.8",
                    "promContent": "11月10日 22点开抢",
                    "itemTag": "好货内部价",
                    "name2": "蜜桃米露 750毫升",
                    "price2": "￥38",
                    "counterPrice": "¥499",
                    "desc": "蜜桃味江南米酒，初恋味道"
                },
                {
                    "imga": "https://yanxuan-item.nosdn.127.net/5e27836d8156e62064dfa3d442eb4d2a.png?imageView&quality=95&thumbnail=245x245",
                    "imgb": "https://yanxuan-item.nosdn.127.net/2d102976777b02d687de895761b2d0de.jpg?quality=95&thumbnail=245x245&imageView",
                    "promoLogo": "https://yanxuan.nosdn.127.net/bf43c8b8b8c205b14e3ac27021e04394.png",
                    "promBanner": "https://yanxuan.nosdn.127.net/5e5ba7f9c3805cc8085368ed41aaff65.png",
                    "promTitle": "https://yanxuan.nosdn.127.net/ced6f7cfbd566e260ea67ec486cb9b60.png",
                    "name": "狂欢特惠",
                    "price": "¥99",
                    "promContent": "仅剩7天",
                    "itemTag": "狂欢特惠",
                    "name2": "996五宝茶",
                    "price2": "¥99",
                    "counterPrice": "¥139",
                    "desc": "添加玛咖粉，找回理想状态"
                },
                {
                    "imga": "https://yanxuan-item.nosdn.127.net/bf4565ead98a56505108fefd2c72f5bb.png?imageView&quality=95&thumbnail=245x245",
                    "imgb": "https://yanxuan-item.nosdn.127.net/8e2f7471316c8ebe611ae1e484826d90.jpg?quality=95&thumbnail=245x245&imageView",
                    "promoLogo": "https://yanxuan.nosdn.127.net/bf43c8b8b8c205b14e3ac27021e04394.png",
                    "promBanner": "https://yanxuan.nosdn.127.net/5e5ba7f9c3805cc8085368ed41aaff65.png",
                    "promTitle": "https://yanxuan.nosdn.127.net/ced6f7cfbd566e260ea67ec486cb9b60.png",
                    "name": "狂欢特惠",
                    "price": "¥99",
                    "promContent": "仅剩7天",
                    "itemTag": "狂欢特惠",
                    "name2": "996五宝茶",
                    "price2": "¥99",
                    "counterPrice": "¥139",
                    "desc": "添加玛咖粉，找回理想状态"
                },
                {
                    "imga": "https://yanxuan-item.nosdn.127.net/8a0ec3908890562b17fceb0641b0a93b.png?imageView&quality=95&thumbnail=245x245",
                    "imgb": "https://yanxuan-item.nosdn.127.net/373d580ae4d7ce6c5af2cfa0bfa041a6.jpg?quality=95&thumbnail=245x245&imageView",
                    "promoLogo": "https://yanxuan.nosdn.127.net/bf43c8b8b8c205b14e3ac27021e04394.png",
                    "promBanner": "https://yanxuan.nosdn.127.net/5e5ba7f9c3805cc8085368ed41aaff65.png",
                    "promTitle": "https://yanxuan.nosdn.127.net/ced6f7cfbd566e260ea67ec486cb9b60.png",
                    "name": "狂欢特惠",
                    "price": "¥99",
                    "promContent": "仅剩7天",
                    "itemTag": "狂欢特惠",
                    "name2": "996五宝茶",
                    "price2": "¥99",
                    "counterPrice": "¥139",
                    "desc": "添加玛咖粉，找回理想状态"
                },
                {
                    "imga": "https://yanxuan-item.nosdn.127.net/61c28f159ac2dd624fc6016eb7035a09.png?imageView&quality=95&thumbnail=245x245",
                    "imgb": "https://yanxuan-item.nosdn.127.net/00bf972b3793742d37da0adb63d27f9d.jpg?quality=95&thumbnail=245x245&imageView",
                    "promoLogo": "https://yanxuan.nosdn.127.net/bf43c8b8b8c205b14e3ac27021e04394.png",
                    "promBanner": "https://yanxuan.nosdn.127.net/5e5ba7f9c3805cc8085368ed41aaff65.png",
                    "promTitle": "https://yanxuan.nosdn.127.net/ced6f7cfbd566e260ea67ec486cb9b60.png",
                    "name": "超级疯抢日",
                    "price": "¥29.8",
                    "promContent": "11月10日 22点开抢",
                    "itemTag": "好货内部价",
                    "name2": "蜜桃米露 750毫升",
                    "price2": "￥38",
                    "counterPrice": "¥499",
                    "desc": "蜜桃味江南米酒，初恋味道"
                }, {
                    "imga": "https://yanxuan-item.nosdn.127.net/851ee663af0a8aceb9eeb3a2c102c152.png?imageView&quality=95&thumbnail=245x245",
                    "imgb": "https://yanxuan-item.nosdn.127.net/085182f83552c6113c5e4910805828ac.png?quality=95&thumbnail=245x245&imageView",
                    "promoLogo": "https://yanxuan.nosdn.127.net/bf43c8b8b8c205b14e3ac27021e04394.png",
                    "promBanner": "https://yanxuan.nosdn.127.net/5e5ba7f9c3805cc8085368ed41aaff65.png",
                    "promTitle": "https://yanxuan.nosdn.127.net/ced6f7cfbd566e260ea67ec486cb9b60.png",
                    "name": "好货内部价",
                    "price": "¥399",
                    "promContent": "仅剩3天",
                    "itemTag": "好货内部价",
                    "name2": "60s臻密绒磨毛四件套",
                    "price2": "¥499",
                    "counterPrice": "¥499",
                    "desc": "浅绒如脂臻密，高级莫兰迪色系"
                }, {

                    "imga": "https://yanxuan-item.nosdn.127.net/edc3848a378e3139078c8370ab5c454c.png?imageView&quality=95&thumbnail=245x245",
                    "imgb": "https://yanxuan-item.nosdn.127.net/f5cdcb14fd603b4f289f1196cf970728.jpg?quality=95&thumbnail=245x245&imageView",
                    "promoLogo": "https://yanxuan.nosdn.127.net/bf43c8b8b8c205b14e3ac27021e04394.png",
                    "promBanner": "https://yanxuan.nosdn.127.net/5e5ba7f9c3805cc8085368ed41aaff65.png",
                    "promTitle": "https://yanxuan.nosdn.127.net/ced6f7cfbd566e260ea67ec486cb9b60.png",
                    "name": "超级疯抢日",
                    "price": "¥29.8",
                    "promContent": "11月10日 22点开抢",
                    "itemTag": "好货内部价",
                    "name2": "蜜桃米露 750毫升",
                    "price2": "￥38",
                    "counterPrice": "¥499",
                    "desc": "蜜桃味江南米酒，初恋味道"
                }, {

                    "imga": "https://yanxuan-item.nosdn.127.net/4ee217e80e59c814579d822a6f6af251.png?imageView&quality=95&thumbnail=245x245",
                    "imgb": "https://yanxuan-item.nosdn.127.net/033de4334fcf027b63ab865799896643.jpg?quality=95&thumbnail=245x245&imageView",
                    "promoLogo": "https://yanxuan.nosdn.127.net/bf43c8b8b8c205b14e3ac27021e04394.png",
                    "promBanner": "https://yanxuan.nosdn.127.net/5e5ba7f9c3805cc8085368ed41aaff65.png",
                    "promTitle": "https://yanxuan.nosdn.127.net/ced6f7cfbd566e260ea67ec486cb9b60.png",
                    "name": "超级疯抢日",
                    "price": "¥29.8",
                    "promContent": "11月10日 22点开抢",
                    "itemTag": "好货内部价",
                    "name2": "蜜桃米露 750毫升",
                    "price2": "￥38",
                    "counterPrice": "¥499",
                    "desc": "蜜桃味江南米酒，初恋味道"
                }, {

                    "imga": "https://yanxuan-item.nosdn.127.net/7251d5f3ac040bc5d58d42f0a58ba957.png?imageView&quality=95&thumbnail=245x245",
                    "imgb": "https://yanxuan-item.nosdn.127.net/da7399246f585ced033c5f351dc69520.jpg?quality=95&thumbnail=245x245&imageView",
                    "promoLogo": "https://yanxuan.nosdn.127.net/bf43c8b8b8c205b14e3ac27021e04394.png",
                    "promBanner": "https://yanxuan.nosdn.127.net/5e5ba7f9c3805cc8085368ed41aaff65.png",
                    "promTitle": "https://yanxuan.nosdn.127.net/ced6f7cfbd566e260ea67ec486cb9b60.png",
                    "name": "超级疯抢日",
                    "price": "¥29.8",
                    "promContent": "11月10日 22点开抢",
                    "itemTag": "好货内部价",
                    "name2": "蜜桃米露 750毫升",
                    "price2": "￥38",
                    "counterPrice": "¥499",
                    "desc": "蜜桃味江南米酒，初恋味道"
                }, {

                    "imga": "https://yanxuan-item.nosdn.127.net/61cea4d145df8eb3a945d2e5d6cc4f90.png?imageView&quality=95&thumbnail=245x245",
                    "imgb": "https://yanxuan-item.nosdn.127.net/a91c8269ad0558819e56328854e6ccef.jpg?quality=95&thumbnail=245x245&imageView",
                    "promoLogo": "https://yanxuan.nosdn.127.net/bf43c8b8b8c205b14e3ac27021e04394.png",
                    "promBanner": "https://yanxuan.nosdn.127.net/5e5ba7f9c3805cc8085368ed41aaff65.png",
                    "promTitle": "https://yanxuan.nosdn.127.net/ced6f7cfbd566e260ea67ec486cb9b60.png",
                    "name": "超级疯抢日",
                    "price": "¥29.8",
                    "promContent": "11月10日 22点开抢",
                    "itemTag": "好货内部价",
                    "name2": "蜜桃米露 750毫升",
                    "price2": "￥38",
                    "counterPrice": "¥499",
                    "desc": "蜜桃味江南米酒，初恋味道"
                }
            ]
        }
    ]
]